<?xml version="1.0" encoding="UTF-8" ?>
<!DOCTYPE mapper PUBLIC "-//mybatis.org//DTD Mapper 3.0//EN" "http://mybatis.org/dtd/mybatis-3-mapper.dtd">
<mapper namespace="com.c.infrastructure.dao.McpGatewayDao">

    <resultMap id="mcpGatewayMap" type="com.c.infrastructure.dao.po.McpGatewayPO">
        <id property="id" column="id" jdbcType="BIGINT"/>
        <result property="gatewayId" column="gateway_id" jdbcType="VARCHAR"/>
        <result property="gatewayName" column="gateway_name" jdbcType="VARCHAR"/>
        <result property="gatewayDescription" column="gateway_description" jdbcType="VARCHAR"/>
        <result property="gatewayVersion" column="gateway_version" jdbcType="VARCHAR"/>
        <result property="status" column="status" jdbcType="INTEGER"/>
        <result property="auth" column="auth" jdbcType="INTEGER"/>
        <result property="createTime" column="create_time" jdbcType="TIMESTAMP"/>
        <result property="updateTime" column="update_time" jdbcType="TIMESTAMP"/>
        <result property="version" column="version" jdbcType="BIGINT"/>
    </resultMap>

    <sql id="all_columns">
        id, gateway_id, gateway_name, gateway_description, gateway_version, status, auth, create_time, update_time, version
    </sql>

    <sql id="query_condition">
        <where>
            <if test="keyword != null and keyword.trim() != ''">
                (gateway_name LIKE CONCAT('%', #{keyword}, '%') OR gateway_id LIKE CONCAT('%', #{keyword}, '%'))
            </if>
            <if test="status != null">
                AND status = #{status}
            </if>
        </where>
    </sql>

    <select id="queryGatewayConfigPage" resultMap="mcpGatewayMap">
        SELECT
        <include refid="all_columns"/>
        FROM mcp_gateway
        <include refid="query_condition"/>
        ORDER BY create_time DESC
        LIMIT #{offset}, #{pageSize}
    </select>

    <select id="queryGatewayConfigCount" resultType="long">
        SELECT COUNT(*) FROM mcp_gateway
        <include refid="query_condition"/>
    </select>

    <select id="findGatewayById" resultMap="mcpGatewayMap">
        SELECT
        <include refid="all_columns"/>
        FROM mcp_gateway
        WHERE gateway_id = #{gatewayId} LIMIT 1
    </select>

    <insert id="insertGateway" useGeneratedKeys="true" keyProperty="id">
        INSERT INTO mcp_gateway
        (gateway_id, gateway_name, gateway_description, gateway_version, status, auth, create_time, update_time, version)
        VALUES (#{gatewayId}, #{gatewayName}, #{gatewayDescription}, #{gatewayVersion}, #{status}, #{auth}, NOW(), NOW(), 1)
    </insert>

    <update id="updateGatewayStatusByCas">
        UPDATE mcp_gateway
        SET status      = #{status},
            update_time = NOW(),
            version     = version + 1
        WHERE gateway_id = #{gatewayId}
          AND version = #{oldVersion}
    </update>

    <delete id="deleteGateway">
        DELETE
        FROM mcp_gateway
        WHERE gateway_id = #{gatewayId}
    </delete>

    <update id="publishGateway">
        UPDATE mcp_gateway
        SET status      = 1,
            update_time = NOW()
        WHERE gateway_id = #{gatewayId}
    </update>

    <update id="offlineGateway">
        UPDATE mcp_gateway
        SET status      = 0,
            update_time = NOW()
        WHERE gateway_id = #{gatewayId}
    </update>

    <update id="updateById">
        UPDATE mcp_gateway
        <set>
            <if test="gatewayId != null">gateway_id = #{gatewayId},</if>
            <if test="gatewayName != null">gateway_name = #{gatewayName},</if>
            <if test="gatewayDescription != null">gateway_description = #{gatewayDescription},</if>
            <if test="gatewayVersion != null">gateway_version = #{gatewayVersion},</if>
            <if test="status != null">status = #{status},</if>
            <if test="auth != null">auth = #{auth},</if>
            update_time = NOW()
        </set>
        WHERE id = #{id}
    </update>

    <update id="updateByGatewayId">
        UPDATE mcp_gateway
        <set>
            <if test="gatewayName != null">gateway_name = #{gatewayName},</if>
            <if test="gatewayDescription != null">gateway_description = #{gatewayDescription},</if>
            <if test="gatewayVersion != null">gateway_version = #{gatewayVersion},</if>
            <if test="status != null">status = #{status},</if>
            <if test="auth != null">auth = #{auth},</if>
            update_time = NOW()
        </set>
        WHERE gateway_id = #{gatewayId}
    </update>

    <select id="queryAll" resultMap="mcpGatewayMap">
        SELECT
        <include refid="all_columns"/>
        FROM mcp_gateway ORDER BY create_time DESC
    </select>

    <select id="queryByGatewayId" resultMap="mcpGatewayMap">
        SELECT
        <include refid="all_columns"/>
        FROM mcp_gateway WHERE gateway_id = #{gatewayId} LIMIT 1
    </select>

    <select id="queryById" resultMap="mcpGatewayMap">
        SELECT
        <include refid="all_columns"/>
        FROM mcp_gateway WHERE id = #{id}
    </select>

    <select id="queryByGatewayIds" resultMap="mcpGatewayMap">
        SELECT
        <include refid="all_columns"/>
        FROM mcp_gateway
        WHERE gateway_id IN
        <foreach collection="gatewayIds" item="gatewayId" open="(" separator="," close=")">
            #{gatewayId}
        </foreach>
    </select>

    <delete id="deleteById">
        DELETE
        FROM mcp_gateway
        WHERE id = #{id}
    </delete>

    <update id="updateAuthStatusByGatewayId">
        UPDATE mcp_gateway
        SET auth        = #{auth},
            update_time = NOW()
        WHERE gateway_id = #{gatewayId}
    </update>

    <update id="updateGatewayByCas">
        UPDATE mcp_gateway
        <set>
            <if test="po.gatewayName != null">gateway_name = #{po.gatewayName},</if>
            <if test="po.gatewayDescription != null">gateway_description = #{po.gatewayDescription},</if>
            <if test="po.gatewayVersion != null">gateway_version = #{po.gatewayVersion},</if>
            <if test="po.status != null">status = #{po.status},</if>
            <if test="po.auth != null">auth = #{po.auth},</if>
            update_time = NOW(),
            version = version + 1
        </set>
        WHERE gateway_id = #{po.gatewayId}
        AND version = #{oldVersion}
    </update>

</mapper>